README.rst
setup.py
eiscp/__init__.py
eiscp/commands.py
eiscp/core.py
eiscp/script.py
eiscp/utils.py
onkyo_eiscp.egg-info/PKG-INFO
onkyo_eiscp.egg-info/SOURCES.txt
onkyo_eiscp.egg-info/dependency_links.txt
onkyo_eiscp.egg-info/entry_points.txt
onkyo_eiscp.egg-info/requires.txt
onkyo_eiscp.egg-info/top_level.txt
tests/__init__.py
tests/test_core.py