Metadata-Version: 1.1
Name: onkyo-eiscp
Version: 1.2.5
Summary: Control Onkyo receivers over ethernet.
Home-page: https://github.com/miracle2k/onkyo-eiscp
Author: Michael Elsdörfer
Author-email: michael@elsdoerfer.com
License: MIT
Platform: any
Classifier: Topic :: System :: Networking
Classifier: Topic :: Games/Entertainment
Classifier: Topic :: Multimedia
Classifier: Intended Audience :: Developers
Classifier: Intended Audience :: End Users/Desktop
Classifier: License :: OSI Approved :: MIT License
Classifier: Operating System :: OS Independent
Classifier: Programming Language :: Python
